{"plot_kind": "next_day", "timezone": "Europe/Amsterdam", "metadata": {}, "rows": [{"target_time_utc": "2026-06-04T22:00:00Z", "target_time_local": "2026-06-05T00:00:00+0200", "hour_utc": 22, "hour_local": 0, "forecast_wind_speed": 12.0, "forecast_wind_min": 12.0, "forecast_wind_max": 22.0, "lstm_pred_wind_speed": 10.109831, "delta_speed_lstm_minus_forecast": -1.8901691, "forecast_wind_dir_deg": 224.0, "lstm_pred_wind_dir_deg": 222.09117, "delta_dir_lstm_minus_forecast": -1.9088287}, {"target_time_utc": "2026-06-04T23:00:00Z", "target_time_local": "2026-06-05T01:00:00+0200", "hour_utc": 23, "hour_local": 1, "forecast_wind_speed": 12.0, "forecast_wind_min": 12.0, "forecast_wind_max": 21.0, "lstm_pred_wind_speed": 9.768637, "delta_speed_lstm_minus_forecast": -2.2313633, "forecast_wind_dir_deg": 229.0, "lstm_pred_wind_dir_deg": 225.54082, "delta_dir_lstm_minus_forecast": -3.4591827}, {"target_time_utc": "2026-06-05T00:00:00Z", "target_time_local": "2026-06-05T02:00:00+0200", "hour_utc": 0, "hour_local": 2, "forecast_wind_speed": 14.0, "forecast_wind_min": 14.0, "forecast_wind_max": 25.0, "lstm_pred_wind_speed": 11.83333, "delta_speed_lstm_minus_forecast": -2.1666698, "forecast_wind_dir_deg": 242.0, "lstm_pred_wind_dir_deg": 239.48619, "delta_dir_lstm_minus_forecast": -2.5138092}, {"target_time_utc": "2026-06-05T01:00:00Z", "target_time_local": "2026-06-05T03:00:00+0200", "hour_utc": 1, "hour_local": 3, "forecast_wind_speed": 13.0, "forecast_wind_min": 13.0, "forecast_wind_max": 27.0, "lstm_pred_wind_speed": 11.250866, "delta_speed_lstm_minus_forecast": -1.7491341, "forecast_wind_dir_deg": 239.0, "lstm_pred_wind_dir_deg": 236.83392, "delta_dir_lstm_minus_forecast": -2.1660767}, {"target_time_utc": "2026-06-05T02:00:00Z", "target_time_local": "2026-06-05T04:00:00+0200", "hour_utc": 2, "hour_local": 4, "forecast_wind_speed": 10.0, "forecast_wind_min": 10.0, "forecast_wind_max": 24.0, "lstm_pred_wind_speed": 8.354966, "delta_speed_lstm_minus_forecast": -1.6450338, "forecast_wind_dir_deg": 245.0, "lstm_pred_wind_dir_deg": 241.10008, "delta_dir_lstm_minus_forecast": -3.8999176}, {"target_time_utc": "2026-06-05T03:00:00Z", "target_time_local": "2026-06-05T05:00:00+0200", "hour_utc": 3, "hour_local": 5, "forecast_wind_speed": 12.0, "forecast_wind_min": 12.0, "forecast_wind_max": 22.0, "lstm_pred_wind_speed": 9.986007, "delta_speed_lstm_minus_forecast": -2.0139933, "forecast_wind_dir_deg": 255.0, "lstm_pred_wind_dir_deg": 253.28677, "delta_dir_lstm_minus_forecast": -1.7132263}, {"target_time_utc": "2026-06-05T04:00:00Z", "target_time_local": "2026-06-05T06:00:00+0200", "hour_utc": 4, "hour_local": 6, "forecast_wind_speed": 11.0, "forecast_wind_min": 11.0, "forecast_wind_max": 22.0, "lstm_pred_wind_speed": 9.518652, "delta_speed_lstm_minus_forecast": -1.481348, "forecast_wind_dir_deg": 264.0, "lstm_pred_wind_dir_deg": 259.77942, "delta_dir_lstm_minus_forecast": -4.220581}, {"target_time_utc": "2026-06-05T05:00:00Z", "target_time_local": "2026-06-05T07:00:00+0200", "hour_utc": 5, "hour_local": 7, "forecast_wind_speed": 11.0, "forecast_wind_min": 11.0, "forecast_wind_max": 20.0, "lstm_pred_wind_speed": 9.862305, "delta_speed_lstm_minus_forecast": -1.1376953, "forecast_wind_dir_deg": 272.0, "lstm_pred_wind_dir_deg": 267.40234, "delta_dir_lstm_minus_forecast": -4.5976562}, {"target_time_utc": "2026-06-05T06:00:00Z", "target_time_local": "2026-06-05T08:00:00+0200", "hour_utc": 6, "hour_local": 8, "forecast_wind_speed": 9.0, "forecast_wind_min": 9.0, "forecast_wind_max": 19.0, "lstm_pred_wind_speed": 8.559418, "delta_speed_lstm_minus_forecast": -0.44058228, "forecast_wind_dir_deg": 281.0, "lstm_pred_wind_dir_deg": 278.04517, "delta_dir_lstm_minus_forecast": -2.954834}, {"target_time_utc": "2026-06-05T07:00:00Z", "target_time_local": "2026-06-05T09:00:00+0200", "hour_utc": 7, "hour_local": 9, "forecast_wind_speed": 8.0, "forecast_wind_min": 8.0, "forecast_wind_max": 17.0, "lstm_pred_wind_speed": 8.144849, "delta_speed_lstm_minus_forecast": 0.14484882, "forecast_wind_dir_deg": 274.0, "lstm_pred_wind_dir_deg": 272.02042, "delta_dir_lstm_minus_forecast": -1.9795837}, {"target_time_utc": "2026-06-05T08:00:00Z", "target_time_local": "2026-06-05T10:00:00+0200", "hour_utc": 8, "hour_local": 10, "forecast_wind_speed": 9.0, "forecast_wind_min": 9.0, "forecast_wind_max": 17.0, "lstm_pred_wind_speed": 9.497778, "delta_speed_lstm_minus_forecast": 0.49777794, "forecast_wind_dir_deg": 272.0, "lstm_pred_wind_dir_deg": 267.83246, "delta_dir_lstm_minus_forecast": -4.1675415}, {"target_time_utc": "2026-06-05T09:00:00Z", "target_time_local": "2026-06-05T11:00:00+0200", "hour_utc": 9, "hour_local": 11, "forecast_wind_speed": 8.0, "forecast_wind_min": 8.0, "forecast_wind_max": 17.0, "lstm_pred_wind_speed": 9.205039, "delta_speed_lstm_minus_forecast": 1.205039, "forecast_wind_dir_deg": 273.0, "lstm_pred_wind_dir_deg": 264.45508, "delta_dir_lstm_minus_forecast": -8.544922}, {"target_time_utc": "2026-06-05T10:00:00Z", "target_time_local": "2026-06-05T12:00:00+0200", "hour_utc": 10, "hour_local": 12, "forecast_wind_speed": 7.0, "forecast_wind_min": 7.0, "forecast_wind_max": 16.0, "lstm_pred_wind_speed": 8.6668415, "delta_speed_lstm_minus_forecast": 1.6668415, "forecast_wind_dir_deg": 273.0, "lstm_pred_wind_dir_deg": 264.78387, "delta_dir_lstm_minus_forecast": -8.2161255}, {"target_time_utc": "2026-06-05T11:00:00Z", "target_time_local": "2026-06-05T13:00:00+0200", "hour_utc": 11, "hour_local": 13, "forecast_wind_speed": 8.0, "forecast_wind_min": 8.0, "forecast_wind_max": 17.0, "lstm_pred_wind_speed": 9.926467, "delta_speed_lstm_minus_forecast": 1.926467, "forecast_wind_dir_deg": 271.0, "lstm_pred_wind_dir_deg": 261.83707, "delta_dir_lstm_minus_forecast": -9.162933}, {"target_time_utc": "2026-06-05T12:00:00Z", "target_time_local": "2026-06-05T14:00:00+0200", "hour_utc": 12, "hour_local": 14, "forecast_wind_speed": 9.0, "forecast_wind_min": 9.0, "forecast_wind_max": 17.0, "lstm_pred_wind_speed": 10.750984, "delta_speed_lstm_minus_forecast": 1.7509842, "forecast_wind_dir_deg": 274.0, "lstm_pred_wind_dir_deg": 263.9892, "delta_dir_lstm_minus_forecast": -10.010803}, {"target_time_utc": "2026-06-05T13:00:00Z", "target_time_local": "2026-06-05T15:00:00+0200", "hour_utc": 13, "hour_local": 15, "forecast_wind_speed": 9.0, "forecast_wind_min": 9.0, "forecast_wind_max": 18.0, "lstm_pred_wind_speed": 10.725451, "delta_speed_lstm_minus_forecast": 1.7254515, "forecast_wind_dir_deg": 275.0, "lstm_pred_wind_dir_deg": 262.47302, "delta_dir_lstm_minus_forecast": -12.526978}, {"target_time_utc": "2026-06-05T14:00:00Z", "target_time_local": "2026-06-05T16:00:00+0200", "hour_utc": 14, "hour_local": 16, "forecast_wind_speed": 9.0, "forecast_wind_min": 9.0, "forecast_wind_max": 18.0, "lstm_pred_wind_speed": 10.293054, "delta_speed_lstm_minus_forecast": 1.2930536, "forecast_wind_dir_deg": 280.0, "lstm_pred_wind_dir_deg": 270.07718, "delta_dir_lstm_minus_forecast": -9.922821}, {"target_time_utc": "2026-06-05T15:00:00Z", "target_time_local": "2026-06-05T17:00:00+0200", "hour_utc": 15, "hour_local": 17, "forecast_wind_speed": 7.0, "forecast_wind_min": 7.0, "forecast_wind_max": 17.0, "lstm_pred_wind_speed": 8.20346, "delta_speed_lstm_minus_forecast": 1.2034597, "forecast_wind_dir_deg": 274.0, "lstm_pred_wind_dir_deg": 263.87488, "delta_dir_lstm_minus_forecast": -10.125122}, {"target_time_utc": "2026-06-05T16:00:00Z", "target_time_local": "2026-06-05T18:00:00+0200", "hour_utc": 16, "hour_local": 18, "forecast_wind_speed": 6.0, "forecast_wind_min": 6.0, "forecast_wind_max": 15.0, "lstm_pred_wind_speed": 6.6869287, "delta_speed_lstm_minus_forecast": 0.68692875, "forecast_wind_dir_deg": 276.0, "lstm_pred_wind_dir_deg": 266.30182, "delta_dir_lstm_minus_forecast": -9.698181}, {"target_time_utc": "2026-06-05T17:00:00Z", "target_time_local": "2026-06-05T19:00:00+0200", "hour_utc": 17, "hour_local": 19, "forecast_wind_speed": 6.0, "forecast_wind_min": 6.0, "forecast_wind_max": 13.0, "lstm_pred_wind_speed": 5.7873936, "delta_speed_lstm_minus_forecast": -0.21260643, "forecast_wind_dir_deg": 270.0, "lstm_pred_wind_dir_deg": 265.52087, "delta_dir_lstm_minus_forecast": -4.479126}, {"target_time_utc": "2026-06-05T18:00:00Z", "target_time_local": "2026-06-05T20:00:00+0200", "hour_utc": 18, "hour_local": 20, "forecast_wind_speed": 5.0, "forecast_wind_min": 5.0, "forecast_wind_max": 12.0, "lstm_pred_wind_speed": 4.263088, "delta_speed_lstm_minus_forecast": -0.7369118, "forecast_wind_dir_deg": 267.0, "lstm_pred_wind_dir_deg": 257.12317, "delta_dir_lstm_minus_forecast": -9.876831}, {"target_time_utc": "2026-06-05T19:00:00Z", "target_time_local": "2026-06-05T21:00:00+0200", "hour_utc": 19, "hour_local": 21, "forecast_wind_speed": 3.0, "forecast_wind_min": 3.0, "forecast_wind_max": 9.0, "lstm_pred_wind_speed": 1.7385838, "delta_speed_lstm_minus_forecast": -1.2614162, "forecast_wind_dir_deg": 269.0, "lstm_pred_wind_dir_deg": 258.64062, "delta_dir_lstm_minus_forecast": -10.359375}, {"target_time_utc": "2026-06-05T20:00:00Z", "target_time_local": "2026-06-05T22:00:00+0200", "hour_utc": 20, "hour_local": 22, "forecast_wind_speed": 2.0, "forecast_wind_min": 2.0, "forecast_wind_max": 6.0, "lstm_pred_wind_speed": 0.48141015, "delta_speed_lstm_minus_forecast": -1.5185899, "forecast_wind_dir_deg": 247.0, "lstm_pred_wind_dir_deg": 239.1474, "delta_dir_lstm_minus_forecast": -7.8526}, {"target_time_utc": "2026-06-05T21:00:00Z", "target_time_local": "2026-06-05T23:00:00+0200", "hour_utc": 21, "hour_local": 23, "forecast_wind_speed": 3.0, "forecast_wind_min": 3.0, "forecast_wind_max": 4.0, "lstm_pred_wind_speed": 1.6312845, "delta_speed_lstm_minus_forecast": -1.3687155, "forecast_wind_dir_deg": 156.0, "lstm_pred_wind_dir_deg": 146.0184, "delta_dir_lstm_minus_forecast": -9.981598}]}