{"plot_kind": "next_day", "timezone": "Europe/Amsterdam", "metadata": {}, "rows": [{"target_time_utc": "2026-06-07T22:00:00Z", "target_time_local": "2026-06-08T00:00:00+0200", "hour_utc": 22, "hour_local": 0, "forecast_wind_speed": 4.0, "forecast_wind_min": 4.0, "forecast_wind_max": 9.0, "lstm_pred_wind_speed": 1.3417404, "delta_speed_lstm_minus_forecast": -2.6582596, "forecast_wind_dir_deg": 195.0, "lstm_pred_wind_dir_deg": 189.07573, "delta_dir_lstm_minus_forecast": -5.9242706}, {"target_time_utc": "2026-06-07T23:00:00Z", "target_time_local": "2026-06-08T01:00:00+0200", "hour_utc": 23, "hour_local": 1, "forecast_wind_speed": 5.0, "forecast_wind_min": 5.0, "forecast_wind_max": 7.0, "lstm_pred_wind_speed": 1.2717698, "delta_speed_lstm_minus_forecast": -3.7282302, "forecast_wind_dir_deg": 167.0, "lstm_pred_wind_dir_deg": 159.81679, "delta_dir_lstm_minus_forecast": -7.1832123}, {"target_time_utc": "2026-06-08T00:00:00Z", "target_time_local": "2026-06-08T02:00:00+0200", "hour_utc": 0, "hour_local": 2, "forecast_wind_speed": 4.0, "forecast_wind_min": 4.0, "forecast_wind_max": 8.0, "lstm_pred_wind_speed": 1.1520054, "delta_speed_lstm_minus_forecast": -2.8479946, "forecast_wind_dir_deg": 173.0, "lstm_pred_wind_dir_deg": 169.64784, "delta_dir_lstm_minus_forecast": -3.3521576}, {"target_time_utc": "2026-06-08T01:00:00Z", "target_time_local": "2026-06-08T03:00:00+0200", "hour_utc": 1, "hour_local": 3, "forecast_wind_speed": 5.0, "forecast_wind_min": 5.0, "forecast_wind_max": 9.0, "lstm_pred_wind_speed": 1.8229802, "delta_speed_lstm_minus_forecast": -3.1770198, "forecast_wind_dir_deg": 185.0, "lstm_pred_wind_dir_deg": 176.68304, "delta_dir_lstm_minus_forecast": -8.316956}, {"target_time_utc": "2026-06-08T02:00:00Z", "target_time_local": "2026-06-08T04:00:00+0200", "hour_utc": 2, "hour_local": 4, "forecast_wind_speed": 5.0, "forecast_wind_min": 5.0, "forecast_wind_max": 9.0, "lstm_pred_wind_speed": 1.933059, "delta_speed_lstm_minus_forecast": -3.066941, "forecast_wind_dir_deg": 187.0, "lstm_pred_wind_dir_deg": 180.40013, "delta_dir_lstm_minus_forecast": -6.599869}, {"target_time_utc": "2026-06-08T03:00:00Z", "target_time_local": "2026-06-08T05:00:00+0200", "hour_utc": 3, "hour_local": 5, "forecast_wind_speed": 5.0, "forecast_wind_min": 5.0, "forecast_wind_max": 8.0, "lstm_pred_wind_speed": 1.7512155, "delta_speed_lstm_minus_forecast": -3.2487845, "forecast_wind_dir_deg": 167.0, "lstm_pred_wind_dir_deg": 159.32703, "delta_dir_lstm_minus_forecast": -7.6729736}, {"target_time_utc": "2026-06-08T04:00:00Z", "target_time_local": "2026-06-08T06:00:00+0200", "hour_utc": 4, "hour_local": 6, "forecast_wind_speed": 5.0, "forecast_wind_min": 5.0, "forecast_wind_max": 8.0, "lstm_pred_wind_speed": 1.8947191, "delta_speed_lstm_minus_forecast": -3.1052809, "forecast_wind_dir_deg": 151.0, "lstm_pred_wind_dir_deg": 142.23305, "delta_dir_lstm_minus_forecast": -8.7669525}, {"target_time_utc": "2026-06-08T05:00:00Z", "target_time_local": "2026-06-08T07:00:00+0200", "hour_utc": 5, "hour_local": 7, "forecast_wind_speed": 7.0, "forecast_wind_min": 7.0, "forecast_wind_max": 11.0, "lstm_pred_wind_speed": 3.6945968, "delta_speed_lstm_minus_forecast": -3.3054032, "forecast_wind_dir_deg": 154.0, "lstm_pred_wind_dir_deg": 145.1453, "delta_dir_lstm_minus_forecast": -8.854706}, {"target_time_utc": "2026-06-08T06:00:00Z", "target_time_local": "2026-06-08T08:00:00+0200", "hour_utc": 6, "hour_local": 8, "forecast_wind_speed": 7.0, "forecast_wind_min": 7.0, "forecast_wind_max": 12.0, "lstm_pred_wind_speed": 4.5150976, "delta_speed_lstm_minus_forecast": -2.4849024, "forecast_wind_dir_deg": 153.0, "lstm_pred_wind_dir_deg": 144.52132, "delta_dir_lstm_minus_forecast": -8.478683}, {"target_time_utc": "2026-06-08T07:00:00Z", "target_time_local": "2026-06-08T09:00:00+0200", "hour_utc": 7, "hour_local": 9, "forecast_wind_speed": 8.0, "forecast_wind_min": 8.0, "forecast_wind_max": 14.0, "lstm_pred_wind_speed": 5.87402, "delta_speed_lstm_minus_forecast": -2.12598, "forecast_wind_dir_deg": 149.0, "lstm_pred_wind_dir_deg": 141.40173, "delta_dir_lstm_minus_forecast": -7.5982666}, {"target_time_utc": "2026-06-08T08:00:00Z", "target_time_local": "2026-06-08T10:00:00+0200", "hour_utc": 8, "hour_local": 10, "forecast_wind_speed": 7.0, "forecast_wind_min": 7.0, "forecast_wind_max": 14.0, "lstm_pred_wind_speed": 6.2608433, "delta_speed_lstm_minus_forecast": -0.7391567, "forecast_wind_dir_deg": 156.0, "lstm_pred_wind_dir_deg": 144.60979, "delta_dir_lstm_minus_forecast": -11.390213}, {"target_time_utc": "2026-06-08T09:00:00Z", "target_time_local": "2026-06-08T11:00:00+0200", "hour_utc": 9, "hour_local": 11, "forecast_wind_speed": 6.0, "forecast_wind_min": 6.0, "forecast_wind_max": 12.0, "lstm_pred_wind_speed": 6.059429, "delta_speed_lstm_minus_forecast": 0.05942917, "forecast_wind_dir_deg": 162.0, "lstm_pred_wind_dir_deg": 150.1095, "delta_dir_lstm_minus_forecast": -11.890503}, {"target_time_utc": "2026-06-08T10:00:00Z", "target_time_local": "2026-06-08T12:00:00+0200", "hour_utc": 10, "hour_local": 12, "forecast_wind_speed": 6.0, "forecast_wind_min": 6.0, "forecast_wind_max": 12.0, "lstm_pred_wind_speed": 6.638439, "delta_speed_lstm_minus_forecast": 0.6384392, "forecast_wind_dir_deg": 170.0, "lstm_pred_wind_dir_deg": 160.84622, "delta_dir_lstm_minus_forecast": -9.153778}, {"target_time_utc": "2026-06-08T11:00:00Z", "target_time_local": "2026-06-08T13:00:00+0200", "hour_utc": 11, "hour_local": 13, "forecast_wind_speed": 6.0, "forecast_wind_min": 6.0, "forecast_wind_max": 12.0, "lstm_pred_wind_speed": 6.9209776, "delta_speed_lstm_minus_forecast": 0.9209776, "forecast_wind_dir_deg": 171.0, "lstm_pred_wind_dir_deg": 162.60078, "delta_dir_lstm_minus_forecast": -8.399216}, {"target_time_utc": "2026-06-08T12:00:00Z", "target_time_local": "2026-06-08T14:00:00+0200", "hour_utc": 12, "hour_local": 14, "forecast_wind_speed": 7.0, "forecast_wind_min": 7.0, "forecast_wind_max": 14.0, "lstm_pred_wind_speed": 8.210391, "delta_speed_lstm_minus_forecast": 1.210391, "forecast_wind_dir_deg": 178.0, "lstm_pred_wind_dir_deg": 171.99356, "delta_dir_lstm_minus_forecast": -6.006439}, {"target_time_utc": "2026-06-08T13:00:00Z", "target_time_local": "2026-06-08T15:00:00+0200", "hour_utc": 13, "hour_local": 15, "forecast_wind_speed": 9.0, "forecast_wind_min": 9.0, "forecast_wind_max": 19.0, "lstm_pred_wind_speed": 11.074131, "delta_speed_lstm_minus_forecast": 2.074131, "forecast_wind_dir_deg": 198.0, "lstm_pred_wind_dir_deg": 189.0029, "delta_dir_lstm_minus_forecast": -8.997101}, {"target_time_utc": "2026-06-08T14:00:00Z", "target_time_local": "2026-06-08T16:00:00+0200", "hour_utc": 14, "hour_local": 16, "forecast_wind_speed": 8.0, "forecast_wind_min": 8.0, "forecast_wind_max": 16.0, "lstm_pred_wind_speed": 8.779589, "delta_speed_lstm_minus_forecast": 0.7795887, "forecast_wind_dir_deg": 212.0, "lstm_pred_wind_dir_deg": 200.33774, "delta_dir_lstm_minus_forecast": -11.662262}, {"target_time_utc": "2026-06-08T15:00:00Z", "target_time_local": "2026-06-08T17:00:00+0200", "hour_utc": 15, "hour_local": 17, "forecast_wind_speed": 7.0, "forecast_wind_min": 7.0, "forecast_wind_max": 15.0, "lstm_pred_wind_speed": 6.7530503, "delta_speed_lstm_minus_forecast": -0.24694967, "forecast_wind_dir_deg": 230.0, "lstm_pred_wind_dir_deg": 221.19405, "delta_dir_lstm_minus_forecast": -8.805954}, {"target_time_utc": "2026-06-08T16:00:00Z", "target_time_local": "2026-06-08T18:00:00+0200", "hour_utc": 16, "hour_local": 18, "forecast_wind_speed": 9.0, "forecast_wind_min": 9.0, "forecast_wind_max": 15.0, "lstm_pred_wind_speed": 7.869508, "delta_speed_lstm_minus_forecast": -1.1304922, "forecast_wind_dir_deg": 238.0, "lstm_pred_wind_dir_deg": 226.5577, "delta_dir_lstm_minus_forecast": -11.4423065}, {"target_time_utc": "2026-06-08T17:00:00Z", "target_time_local": "2026-06-08T19:00:00+0200", "hour_utc": 17, "hour_local": 19, "forecast_wind_speed": 10.0, "forecast_wind_min": 10.0, "forecast_wind_max": 19.0, "lstm_pred_wind_speed": 8.693089, "delta_speed_lstm_minus_forecast": -1.3069115, "forecast_wind_dir_deg": 236.0, "lstm_pred_wind_dir_deg": 224.44354, "delta_dir_lstm_minus_forecast": -11.5564575}, {"target_time_utc": "2026-06-08T18:00:00Z", "target_time_local": "2026-06-08T20:00:00+0200", "hour_utc": 18, "hour_local": 20, "forecast_wind_speed": 10.0, "forecast_wind_min": 10.0, "forecast_wind_max": 22.0, "lstm_pred_wind_speed": 8.627245, "delta_speed_lstm_minus_forecast": -1.372755, "forecast_wind_dir_deg": 234.0, "lstm_pred_wind_dir_deg": 223.77898, "delta_dir_lstm_minus_forecast": -10.221024}, {"target_time_utc": "2026-06-08T19:00:00Z", "target_time_local": "2026-06-08T21:00:00+0200", "hour_utc": 19, "hour_local": 21, "forecast_wind_speed": 12.0, "forecast_wind_min": 12.0, "forecast_wind_max": 21.0, "lstm_pred_wind_speed": 9.714314, "delta_speed_lstm_minus_forecast": -2.2856855, "forecast_wind_dir_deg": 238.0, "lstm_pred_wind_dir_deg": 229.06906, "delta_dir_lstm_minus_forecast": -8.930939}, {"target_time_utc": "2026-06-08T20:00:00Z", "target_time_local": "2026-06-08T22:00:00+0200", "hour_utc": 20, "hour_local": 22, "forecast_wind_speed": 12.0, "forecast_wind_min": 12.0, "forecast_wind_max": 23.0, "lstm_pred_wind_speed": 9.632049, "delta_speed_lstm_minus_forecast": -2.3679514, "forecast_wind_dir_deg": 242.0, "lstm_pred_wind_dir_deg": 232.4778, "delta_dir_lstm_minus_forecast": -9.522202}, {"target_time_utc": "2026-06-08T21:00:00Z", "target_time_local": "2026-06-08T23:00:00+0200", "hour_utc": 21, "hour_local": 23, "forecast_wind_speed": 10.0, "forecast_wind_min": 10.0, "forecast_wind_max": 21.0, "lstm_pred_wind_speed": 7.390628, "delta_speed_lstm_minus_forecast": -2.6093721, "forecast_wind_dir_deg": 243.0, "lstm_pred_wind_dir_deg": 235.60109, "delta_dir_lstm_minus_forecast": -7.3989105}]}