{"plot_kind": "next_day", "timezone": "Europe/Amsterdam", "metadata": {}, "rows": [{"target_time_utc": "2026-06-05T22:00:00Z", "target_time_local": "2026-06-06T00:00:00+0200", "hour_utc": 22, "hour_local": 0, "forecast_wind_speed": 5.0, "forecast_wind_min": 5.0, "forecast_wind_max": 7.0, "lstm_pred_wind_speed": 2.512537, "delta_speed_lstm_minus_forecast": -2.487463, "forecast_wind_dir_deg": 175.0, "lstm_pred_wind_dir_deg": 173.0243, "delta_dir_lstm_minus_forecast": -1.9756927}, {"target_time_utc": "2026-06-05T23:00:00Z", "target_time_local": "2026-06-06T01:00:00+0200", "hour_utc": 23, "hour_local": 1, "forecast_wind_speed": 5.0, "forecast_wind_min": 5.0, "forecast_wind_max": 7.0, "lstm_pred_wind_speed": 2.59462, "delta_speed_lstm_minus_forecast": -2.40538, "forecast_wind_dir_deg": 190.0, "lstm_pred_wind_dir_deg": 186.97603, "delta_dir_lstm_minus_forecast": -3.0239716}, {"target_time_utc": "2026-06-06T00:00:00Z", "target_time_local": "2026-06-06T02:00:00+0200", "hour_utc": 0, "hour_local": 2, "forecast_wind_speed": 4.0, "forecast_wind_min": 4.0, "forecast_wind_max": 7.0, "lstm_pred_wind_speed": 1.9822408, "delta_speed_lstm_minus_forecast": -2.0177593, "forecast_wind_dir_deg": 154.0, "lstm_pred_wind_dir_deg": 151.70515, "delta_dir_lstm_minus_forecast": -2.2948456}, {"target_time_utc": "2026-06-06T01:00:00Z", "target_time_local": "2026-06-06T03:00:00+0200", "hour_utc": 1, "hour_local": 3, "forecast_wind_speed": 5.0, "forecast_wind_min": 5.0, "forecast_wind_max": 7.0, "lstm_pred_wind_speed": 2.2013407, "delta_speed_lstm_minus_forecast": -2.7986593, "forecast_wind_dir_deg": 154.0, "lstm_pred_wind_dir_deg": 151.82355, "delta_dir_lstm_minus_forecast": -2.1764526}, {"target_time_utc": "2026-06-06T02:00:00Z", "target_time_local": "2026-06-06T04:00:00+0200", "hour_utc": 2, "hour_local": 4, "forecast_wind_speed": 4.0, "forecast_wind_min": 4.0, "forecast_wind_max": 8.0, "lstm_pred_wind_speed": 2.3543818, "delta_speed_lstm_minus_forecast": -1.6456182, "forecast_wind_dir_deg": 159.0, "lstm_pred_wind_dir_deg": 155.81277, "delta_dir_lstm_minus_forecast": -3.1872253}, {"target_time_utc": "2026-06-06T03:00:00Z", "target_time_local": "2026-06-06T05:00:00+0200", "hour_utc": 3, "hour_local": 5, "forecast_wind_speed": 5.0, "forecast_wind_min": 5.0, "forecast_wind_max": 8.0, "lstm_pred_wind_speed": 2.6577404, "delta_speed_lstm_minus_forecast": -2.3422596, "forecast_wind_dir_deg": 143.0, "lstm_pred_wind_dir_deg": 141.36044, "delta_dir_lstm_minus_forecast": -1.6395569}, {"target_time_utc": "2026-06-06T04:00:00Z", "target_time_local": "2026-06-06T06:00:00+0200", "hour_utc": 4, "hour_local": 6, "forecast_wind_speed": 6.0, "forecast_wind_min": 6.0, "forecast_wind_max": 10.0, "lstm_pred_wind_speed": 3.4304998, "delta_speed_lstm_minus_forecast": -2.5695002, "forecast_wind_dir_deg": 141.0, "lstm_pred_wind_dir_deg": 137.33647, "delta_dir_lstm_minus_forecast": -3.6635284}, {"target_time_utc": "2026-06-06T05:00:00Z", "target_time_local": "2026-06-06T07:00:00+0200", "hour_utc": 5, "hour_local": 7, "forecast_wind_speed": 6.0, "forecast_wind_min": 6.0, "forecast_wind_max": 11.0, "lstm_pred_wind_speed": 4.280779, "delta_speed_lstm_minus_forecast": -1.7192211, "forecast_wind_dir_deg": 148.0, "lstm_pred_wind_dir_deg": 143.70534, "delta_dir_lstm_minus_forecast": -4.2946625}, {"target_time_utc": "2026-06-06T06:00:00Z", "target_time_local": "2026-06-06T08:00:00+0200", "hour_utc": 6, "hour_local": 8, "forecast_wind_speed": 6.0, "forecast_wind_min": 6.0, "forecast_wind_max": 11.0, "lstm_pred_wind_speed": 5.0214334, "delta_speed_lstm_minus_forecast": -0.97856665, "forecast_wind_dir_deg": 148.0, "lstm_pred_wind_dir_deg": 145.73228, "delta_dir_lstm_minus_forecast": -2.2677155}, {"target_time_utc": "2026-06-06T07:00:00Z", "target_time_local": "2026-06-06T09:00:00+0200", "hour_utc": 7, "hour_local": 9, "forecast_wind_speed": 7.0, "forecast_wind_min": 7.0, "forecast_wind_max": 14.0, "lstm_pred_wind_speed": 6.680794, "delta_speed_lstm_minus_forecast": -0.31920624, "forecast_wind_dir_deg": 148.0, "lstm_pred_wind_dir_deg": 145.82018, "delta_dir_lstm_minus_forecast": -2.1798248}, {"target_time_utc": "2026-06-06T08:00:00Z", "target_time_local": "2026-06-06T10:00:00+0200", "hour_utc": 8, "hour_local": 10, "forecast_wind_speed": 8.0, "forecast_wind_min": 8.0, "forecast_wind_max": 14.0, "lstm_pred_wind_speed": 8.299036, "delta_speed_lstm_minus_forecast": 0.29903603, "forecast_wind_dir_deg": 160.0, "lstm_pred_wind_dir_deg": 156.27756, "delta_dir_lstm_minus_forecast": -3.7224426}, {"target_time_utc": "2026-06-06T09:00:00Z", "target_time_local": "2026-06-06T11:00:00+0200", "hour_utc": 9, "hour_local": 11, "forecast_wind_speed": 9.0, "forecast_wind_min": 9.0, "forecast_wind_max": 17.0, "lstm_pred_wind_speed": 10.664922, "delta_speed_lstm_minus_forecast": 1.6649218, "forecast_wind_dir_deg": 165.0, "lstm_pred_wind_dir_deg": 157.56178, "delta_dir_lstm_minus_forecast": -7.438217}, {"target_time_utc": "2026-06-06T10:00:00Z", "target_time_local": "2026-06-06T12:00:00+0200", "hour_utc": 10, "hour_local": 12, "forecast_wind_speed": 9.0, "forecast_wind_min": 9.0, "forecast_wind_max": 18.0, "lstm_pred_wind_speed": 11.82492, "delta_speed_lstm_minus_forecast": 2.8249197, "forecast_wind_dir_deg": 171.0, "lstm_pred_wind_dir_deg": 163.84193, "delta_dir_lstm_minus_forecast": -7.158066}, {"target_time_utc": "2026-06-06T11:00:00Z", "target_time_local": "2026-06-06T13:00:00+0200", "hour_utc": 11, "hour_local": 13, "forecast_wind_speed": 10.0, "forecast_wind_min": 10.0, "forecast_wind_max": 21.0, "lstm_pred_wind_speed": 14.028536, "delta_speed_lstm_minus_forecast": 4.028536, "forecast_wind_dir_deg": 173.0, "lstm_pred_wind_dir_deg": 165.36343, "delta_dir_lstm_minus_forecast": -7.636566}, {"target_time_utc": "2026-06-06T12:00:00Z", "target_time_local": "2026-06-06T14:00:00+0200", "hour_utc": 12, "hour_local": 14, "forecast_wind_speed": 11.0, "forecast_wind_min": 11.0, "forecast_wind_max": 20.0, "lstm_pred_wind_speed": 15.235446, "delta_speed_lstm_minus_forecast": 4.235446, "forecast_wind_dir_deg": 198.0, "lstm_pred_wind_dir_deg": 189.41206, "delta_dir_lstm_minus_forecast": -8.587936}, {"target_time_utc": "2026-06-06T13:00:00Z", "target_time_local": "2026-06-06T15:00:00+0200", "hour_utc": 13, "hour_local": 15, "forecast_wind_speed": 9.0, "forecast_wind_min": 9.0, "forecast_wind_max": 20.0, "lstm_pred_wind_speed": 12.939614, "delta_speed_lstm_minus_forecast": 3.9396143, "forecast_wind_dir_deg": 178.0, "lstm_pred_wind_dir_deg": 167.39462, "delta_dir_lstm_minus_forecast": -10.605377}, {"target_time_utc": "2026-06-06T14:00:00Z", "target_time_local": "2026-06-06T16:00:00+0200", "hour_utc": 14, "hour_local": 16, "forecast_wind_speed": 9.0, "forecast_wind_min": 9.0, "forecast_wind_max": 17.0, "lstm_pred_wind_speed": 12.102127, "delta_speed_lstm_minus_forecast": 3.102127, "forecast_wind_dir_deg": 202.0, "lstm_pred_wind_dir_deg": 193.61833, "delta_dir_lstm_minus_forecast": -8.381668}, {"target_time_utc": "2026-06-06T15:00:00Z", "target_time_local": "2026-06-06T17:00:00+0200", "hour_utc": 15, "hour_local": 17, "forecast_wind_speed": 9.0, "forecast_wind_min": 9.0, "forecast_wind_max": 16.0, "lstm_pred_wind_speed": 11.06765, "delta_speed_lstm_minus_forecast": 2.0676498, "forecast_wind_dir_deg": 194.0, "lstm_pred_wind_dir_deg": 185.36668, "delta_dir_lstm_minus_forecast": -8.633316}, {"target_time_utc": "2026-06-06T16:00:00Z", "target_time_local": "2026-06-06T18:00:00+0200", "hour_utc": 16, "hour_local": 18, "forecast_wind_speed": 10.0, "forecast_wind_min": 10.0, "forecast_wind_max": 21.0, "lstm_pred_wind_speed": 12.067926, "delta_speed_lstm_minus_forecast": 2.0679264, "forecast_wind_dir_deg": 190.0, "lstm_pred_wind_dir_deg": 181.46587, "delta_dir_lstm_minus_forecast": -8.534134}, {"target_time_utc": "2026-06-06T17:00:00Z", "target_time_local": "2026-06-06T19:00:00+0200", "hour_utc": 17, "hour_local": 19, "forecast_wind_speed": 8.0, "forecast_wind_min": 8.0, "forecast_wind_max": 18.0, "lstm_pred_wind_speed": 8.876111, "delta_speed_lstm_minus_forecast": 0.87611103, "forecast_wind_dir_deg": 185.0, "lstm_pred_wind_dir_deg": 181.47325, "delta_dir_lstm_minus_forecast": -3.5267487}, {"target_time_utc": "2026-06-06T18:00:00Z", "target_time_local": "2026-06-06T20:00:00+0200", "hour_utc": 18, "hour_local": 20, "forecast_wind_speed": 10.0, "forecast_wind_min": 10.0, "forecast_wind_max": 17.0, "lstm_pred_wind_speed": 9.001946, "delta_speed_lstm_minus_forecast": -0.99805355, "forecast_wind_dir_deg": 186.0, "lstm_pred_wind_dir_deg": 177.81119, "delta_dir_lstm_minus_forecast": -8.188812}, {"target_time_utc": "2026-06-06T19:00:00Z", "target_time_local": "2026-06-06T21:00:00+0200", "hour_utc": 19, "hour_local": 21, "forecast_wind_speed": 9.0, "forecast_wind_min": 9.0, "forecast_wind_max": 18.0, "lstm_pred_wind_speed": 7.9429474, "delta_speed_lstm_minus_forecast": -1.0570526, "forecast_wind_dir_deg": 191.0, "lstm_pred_wind_dir_deg": 181.87671, "delta_dir_lstm_minus_forecast": -9.123291}, {"target_time_utc": "2026-06-06T20:00:00Z", "target_time_local": "2026-06-06T22:00:00+0200", "hour_utc": 20, "hour_local": 22, "forecast_wind_speed": 10.0, "forecast_wind_min": 10.0, "forecast_wind_max": 17.0, "lstm_pred_wind_speed": 7.2718983, "delta_speed_lstm_minus_forecast": -2.7281017, "forecast_wind_dir_deg": 175.0, "lstm_pred_wind_dir_deg": 168.47513, "delta_dir_lstm_minus_forecast": -6.524872}, {"target_time_utc": "2026-06-06T21:00:00Z", "target_time_local": "2026-06-06T23:00:00+0200", "hour_utc": 21, "hour_local": 23, "forecast_wind_speed": 12.0, "forecast_wind_min": 12.0, "forecast_wind_max": 23.0, "lstm_pred_wind_speed": 11.018763, "delta_speed_lstm_minus_forecast": -0.9812374, "forecast_wind_dir_deg": 189.0, "lstm_pred_wind_dir_deg": 180.73067, "delta_dir_lstm_minus_forecast": -8.269333}]}